neurophysiotools/__init__.py
neurophysiotools/neurophysiotools.py
neurophysiotools-0.0.2.dist-info/LICENSE.md
neurophysiotools-0.0.2.dist-info/METADATA
neurophysiotools-0.0.2.dist-info/WHEEL
neurophysiotools-0.0.2.dist-info/top_level.txt
neurophysiotools-0.0.2.dist-info/RECORD
