Metadata-Version: 2.1
Name: neurophysiotools
Version: 0.0.2
Summary: NeurophysioTools: tools for Neurophysiological signals in Python
Home-page: https://github.com/enzomarra/neurophysiotools
Download-URL: https://github.com/enzomarra/neurophysiotools
Author: Vincenzo Marra
Author-email: inmachinasolutions@gmail.com
Maintainer: Vincenzo Marra
Maintainer-email: inmachinasolutions@gmail.com
License: MIT license
Classifier: Intended Audience :: Science/Research
Classifier: Programming Language :: Python
Classifier: License :: OSI Approved :: MIT License
Classifier: Topic :: Scientific/Engineering
Classifier: Operating System :: Microsoft :: Windows
Classifier: Operating System :: Unix
Classifier: Operating System :: MacOS
License-File: LICENSE.md
Requires-Dist: numpy
Requires-Dist: scipy
